pangea_translator/__init__.py
pangea_translator/model/__init__.py
pangea_translator/model/model.py
pangea_translator/translate.py
pangea_translator/translators/__init__.py
pangea_translator/translators/aws_bedrock.py
pangea_translator/translators/azureai.py
pangea_translator/translators/base.py
pangea_translator/translators/claude.py
pangea_translator/translators/cohere.py
pangea_translator/translators/dbrx.py
pangea_translator/translators/gemini.py
pangea_translator/translators/langchain.py
pangea_translator/translators/mistral.py
pangea_translator/translators/openai.py
pangea_translator/translators/pangea.py
pangea_translator/translators/plaintext.py
pangea_llm_translator-1.0.2.dist-info/LICENSE
pangea_llm_translator-1.0.2.dist-info/METADATA
pangea_llm_translator-1.0.2.dist-info/WHEEL
pangea_llm_translator-1.0.2.dist-info/RECORD
